{
  "id": "assessment_block6_kvp16_ionisierende_strahlung_v1",
  "lectureCode": "KVP16",
  "title": "Ionisierende Strahlung – Anwendungen in der Medizin",
  "block": "Block 6",
  "sourceSummary": "Physik ionisierender Strahlung, medizinische Anwendungen, Dosimetrie, Radiobiologie, Krebs und Strahlenschutz.",
  "learningObjectives": [
    {
      "id": "lo1",
      "text": "Physikalische Grundlagen ionisierender Strahlung verstehen"
    },
    {
      "id": "lo2",
      "text": "Medizinische Anwendungen ionisierender Strahlung unterscheiden"
    },
    {
      "id": "lo3",
      "text": "Dosisgrössen und Krebsrisiken erklären"
    },
    {
      "id": "lo4",
      "text": "Radiobiologische Mechanismen und DNA-Schäden erklären"
    },
    {
      "id": "lo5",
      "text": "Grundlagen des Strahlenschutzes anwenden"
    }
  ],
  "questions": [
    {
      "id": "q1",
      "type": "A",
      "difficulty": 3,
      "learningObjectiveId": "lo1",
      "stem": "Warum gelten Röntgenstrahlen als ionisierend?",
      "options": [
        {
          "id": "A",
          "text": "Sie sind sichtbar",
          "correct": false
        },
        {
          "id": "B",
          "text": "Sie besitzen genügend Energie zur Ionisation",
          "correct": true
        },
        {
          "id": "C",
          "text": "Sie bestehen aus Radiowellen",
          "correct": false
        },
        {
          "id": "D",
          "text": "Sie sind ungefährlich",
          "correct": false
        },
        {
          "id": "E",
          "text": "Sie stammen nur aus Reaktoren",
          "correct": false
        }
      ],
      "explanation": "Röntgenstrahlen besitzen genügend Energie zur Ionisation von Atomen.",
      "sourceReliability": "high"
    },
    {
      "id": "q2",
      "type": "A",
      "difficulty": 3,
      "learningObjectiveId": "lo1",
      "stem": "Welche Aussage zum elektromagnetischen Spektrum trifft zu?",
      "options": [
        {
          "id": "A",
          "text": "Längere Wellen besitzen höhere Energie",
          "correct": false
        },
        {
          "id": "B",
          "text": "Kürzere Wellen besitzen höhere Energie",
          "correct": true
        },
        {
          "id": "C",
          "text": "Radiowellen sind ionisierend",
          "correct": false
        },
        {
          "id": "D",
          "text": "Mobiltelefone senden Gamma-Strahlung",
          "correct": false
        },
        {
          "id": "E",
          "text": "Sichtbares Licht besitzt höhere Energie als Röntgenstrahlung",
          "correct": false
        }
      ],
      "explanation": "Kurze Wellenlängen entsprechen hohen Energien.",
      "sourceReliability": "high"
    },
    {
      "id": "k1",
      "type": "KPRIM",
      "difficulty": 4,
      "learningObjectiveId": "lo1",
      "stem": "Welche Aussagen zu ionisierender Strahlung stimmen?",
      "options": [
        {
          "id": "A",
          "text": "Röntgenstrahlung ist elektromagnetische Strahlung",
          "correct": true
        },
        {
          "id": "B",
          "text": "Auch Teilchenstrahlung kann ionisierend sein",
          "correct": true
        },
        {
          "id": "C",
          "text": "Mobiltelefonstrahlung ist typischerweise nicht ionisierend",
          "correct": true
        },
        {
          "id": "D",
          "text": "MRT verwendet ionisierende Strahlung",
          "correct": false
        }
      ],
      "explanation": "MRT verwendet keine ionisierende Strahlung.",
      "sourceReliability": "high"
    },
    {
      "id": "q3",
      "type": "A",
      "difficulty": 3,
      "learningObjectiveId": "lo1",
      "stem": "Welche Formel beschreibt die Photonenenergie?",
      "options": [
        {
          "id": "A",
          "text": "E = mgh",
          "correct": false
        },
        {
          "id": "B",
          "text": "E = h·f",
          "correct": true
        },
        {
          "id": "C",
          "text": "E = IR",
          "correct": false
        },
        {
          "id": "D",
          "text": "E = pV",
          "correct": false
        },
        {
          "id": "E",
          "text": "E = mc",
          "correct": false
        }
      ],
      "explanation": "Die Energie eines Photons ist proportional zur Frequenz.",
      "sourceReliability": "high"
    },
    {
      "id": "q4",
      "type": "A",
      "difficulty": 3,
      "learningObjectiveId": "lo2",
      "stem": "Welche Bildgebung verwendet keine ionisierende Strahlung?",
      "options": [
        {
          "id": "A",
          "text": "CT",
          "correct": false
        },
        {
          "id": "B",
          "text": "PET",
          "correct": false
        },
        {
          "id": "C",
          "text": "SPECT",
          "correct": false
        },
        {
          "id": "D",
          "text": "MRT",
          "correct": true
        },
        {
          "id": "E",
          "text": "Angiographie",
          "correct": false
        }
      ],
      "explanation": "MRT arbeitet ohne ionisierende Strahlung.",
      "sourceReliability": "high"
    },
    {
      "id": "k2",
      "type": "KPRIM",
      "difficulty": 4,
      "learningObjectiveId": "lo2",
      "stem": "Welche Verfahren verwenden radioaktive Tracer?",
      "options": [
        {
          "id": "A",
          "text": "PET",
          "correct": true
        },
        {
          "id": "B",
          "text": "SPECT",
          "correct": true
        },
        {
          "id": "C",
          "text": "CT",
          "correct": false
        },
        {
          "id": "D",
          "text": "Planare Röntgenbildgebung",
          "correct": false
        }
      ],
      "explanation": "PET und SPECT gehören zur Nuklearmedizin.",
      "sourceReliability": "high"
    },
    {
      "id": "q5",
      "type": "A",
      "difficulty": 3,
      "learningObjectiveId": "lo2",
      "stem": "Welche Aussage zur CT trifft zu?",
      "options": [
        {
          "id": "A",
          "text": "CT besitzt besseren Weichteilkontrast als MRT",
          "correct": false
        },
        {
          "id": "B",
          "text": "CT besitzt guten Knochenkontrast",
          "correct": true
        },
        {
          "id": "C",
          "text": "CT arbeitet ohne Strahlung",
          "correct": false
        },
        {
          "id": "D",
          "text": "CT verwendet Radiowellen",
          "correct": false
        },
        {
          "id": "E",
          "text": "CT besitzt keine relevante Dosis",
          "correct": false
        }
      ],
      "explanation": "CT eignet sich besonders für Knochenbildgebung.",
      "sourceReliability": "high"
    },
    {
      "id": "q6",
      "type": "A",
      "difficulty": 3,
      "learningObjectiveId": "lo3",
      "stem": "Welche Einheit besitzt die absorbierte Dosis?",
      "options": [
        {
          "id": "A",
          "text": "Sievert",
          "correct": false
        },
        {
          "id": "B",
          "text": "Gray",
          "correct": true
        },
        {
          "id": "C",
          "text": "Tesla",
          "correct": false
        },
        {
          "id": "D",
          "text": "Volt",
          "correct": false
        },
        {
          "id": "E",
          "text": "Becquerel",
          "correct": false
        }
      ],
      "explanation": "Die absorbierte Dosis wird in Gray angegeben.",
      "sourceReliability": "high"
    },
    {
      "id": "k3",
      "type": "KPRIM",
      "difficulty": 4,
      "learningObjectiveId": "lo3",
      "stem": "Welche Aussagen zur Äquivalentdosis stimmen?",
      "options": [
        {
          "id": "A",
          "text": "Sie berücksichtigt biologische Wirkung",
          "correct": true
        },
        {
          "id": "B",
          "text": "Sie wird in Sievert angegeben",
          "correct": true
        },
        {
          "id": "C",
          "text": "Alpha-Strahlung wirkt biologisch stärker als Gamma-Strahlung",
          "correct": true
        },
        {
          "id": "D",
          "text": "Sie beschreibt nur absorbierte Energie",
          "correct": false
        }
      ],
      "explanation": "Die Äquivalentdosis berücksichtigt die biologische Wirkung.",
      "sourceReliability": "high"
    },
    {
      "id": "q7",
      "type": "A",
      "difficulty": 3,
      "learningObjectiveId": "lo3",
      "stem": "Welche Aussage zur effektiven Dosis trifft zu?",
      "options": [
        {
          "id": "A",
          "text": "Sie berücksichtigt nur Strahlungsart",
          "correct": false
        },
        {
          "id": "B",
          "text": "Sie berücksichtigt auch Gewebeempfindlichkeit",
          "correct": true
        },
        {
          "id": "C",
          "text": "Sie wird in Gray angegeben",
          "correct": false
        },
        {
          "id": "D",
          "text": "Sie beschreibt nur lokale Schäden",
          "correct": false
        },
        {
          "id": "E",
          "text": "Sie ist nur für Therapie relevant",
          "correct": false
        }
      ],
      "explanation": "Die effektive Dosis gewichtet zusätzlich Organe.",
      "sourceReliability": "high"
    },
    {
      "id": "q8",
      "type": "A",
      "difficulty": 3,
      "learningObjectiveId": "lo4",
      "stem": "Warum kann ionisierende Strahlung Krebs verursachen?",
      "options": [
        {
          "id": "A",
          "text": "Sie erzeugt nur Wärme",
          "correct": false
        },
        {
          "id": "B",
          "text": "Sie schädigt das Genom",
          "correct": true
        },
        {
          "id": "C",
          "text": "Sie wirkt nur auf Zellmembranen",
          "correct": false
        },
        {
          "id": "D",
          "text": "Sie zerstört nur Proteine",
          "correct": false
        },
        {
          "id": "E",
          "text": "Sie führt nie zu Mutationen",
          "correct": false
        }
      ],
      "explanation": "DNA-Schäden fördern Mutationen und Krebs.",
      "sourceReliability": "high"
    },
    {
      "id": "k4",
      "type": "KPRIM",
      "difficulty": 4,
      "learningObjectiveId": "lo4",
      "stem": "Welche DNA-Schäden nennt die Vorlesung?",
      "options": [
        {
          "id": "A",
          "text": "Einzelstrangbrüche",
          "correct": true
        },
        {
          "id": "B",
          "text": "Doppelstrangbrüche",
          "correct": true
        },
        {
          "id": "C",
          "text": "Inter-Strang-Crosslinks",
          "correct": true
        },
        {
          "id": "D",
          "text": "Myelinverlust",
          "correct": false
        }
      ],
      "explanation": "Die Vorlesung beschreibt mehrere DNA-Schadensformen.",
      "sourceReliability": "high"
    },
    {
      "id": "q9",
      "type": "A",
      "difficulty": 3,
      "learningObjectiveId": "lo4",
      "stem": "Welche Aussage zu indirekten Strahleneffekten ist korrekt?",
      "options": [
        {
          "id": "A",
          "text": "Nur direkte Effekte existieren",
          "correct": false
        },
        {
          "id": "B",
          "text": "Hydrolyseprodukte wie OH-Radikale können DNA schädigen",
          "correct": true
        },
        {
          "id": "C",
          "text": "Wasser spielt keine Rolle",
          "correct": false
        },
        {
          "id": "D",
          "text": "Nur Proteine werden angegriffen",
          "correct": false
        },
        {
          "id": "E",
          "text": "RNA bleibt unbeeinflusst",
          "correct": false
        }
      ],
      "explanation": "Freie Radikale aus Wasser greifen biologische Moleküle an.",
      "sourceReliability": "high"
    },
    {
      "id": "q10",
      "type": "A",
      "difficulty": 3,
      "learningObjectiveId": "lo4",
      "stem": "Welche Aussage zu Krebszellen stimmt?",
      "options": [
        {
          "id": "A",
          "text": "Sie stammen nie von normalen Zellen ab",
          "correct": false
        },
        {
          "id": "B",
          "text": "Krebs beruht auf genetischen Veränderungen",
          "correct": true
        },
        {
          "id": "C",
          "text": "Tumorsuppressorgene fördern Wachstum",
          "correct": false
        },
        {
          "id": "D",
          "text": "Metastasierung gehört nicht zu Krebs",
          "correct": false
        },
        {
          "id": "E",
          "text": "Apoptose ist immer verstärkt",
          "correct": false
        }
      ],
      "explanation": "Krebs beruht auf Veränderungen normaler Zellen.",
      "sourceReliability": "high"
    },
    {
      "id": "k5",
      "type": "KPRIM",
      "difficulty": 4,
      "learningObjectiveId": "lo5",
      "stem": "Welche Massnahmen gehören zum Strahlenschutz?",
      "options": [
        {
          "id": "A",
          "text": "Abstand vergrössern",
          "correct": true
        },
        {
          "id": "B",
          "text": "Bleischutz verwenden",
          "correct": true
        },
        {
          "id": "C",
          "text": "Optimierung und Rechtfertigung",
          "correct": true
        },
        {
          "id": "D",
          "text": "Expositionszeit verlängern",
          "correct": false
        }
      ],
      "explanation": "Abstand, Abschirmung und Optimierung sind zentrale Prinzipien.",
      "sourceReliability": "high"
    },
    {
      "id": "q11",
      "type": "A",
      "difficulty": 3,
      "learningObjectiveId": "lo5",
      "stem": "Was passiert laut inversen Quadratgesetz bei Verdoppelung des Abstands?",
      "options": [
        {
          "id": "A",
          "text": "Dosis verdoppelt sich",
          "correct": false
        },
        {
          "id": "B",
          "text": "Dosis bleibt gleich",
          "correct": false
        },
        {
          "id": "C",
          "text": "Dosis sinkt auf 25 %",
          "correct": true
        },
        {
          "id": "D",
          "text": "Dosis sinkt auf 50 %",
          "correct": false
        },
        {
          "id": "E",
          "text": "Dosis steigt exponentiell",
          "correct": false
        }
      ],
      "explanation": "Die Dosis ist proportional zu 1/r².",
      "sourceReliability": "high"
    },
    {
      "id": "q12",
      "type": "A",
      "difficulty": 3,
      "learningObjectiveId": "lo3",
      "stem": "Welche effektive Dosis wird ungefähr für CT Kopf Perfusion angegeben?",
      "options": [
        {
          "id": "A",
          "text": "0.5 mSv",
          "correct": false
        },
        {
          "id": "B",
          "text": "2 mSv",
          "correct": false
        },
        {
          "id": "C",
          "text": "8 mSv",
          "correct": false
        },
        {
          "id": "D",
          "text": "22 mSv",
          "correct": true
        },
        {
          "id": "E",
          "text": "100 mSv",
          "correct": false
        }
      ],
      "explanation": "CT Kopf Perfusion besitzt hohe Dosen.",
      "sourceReliability": "high"
    },
    {
      "id": "q13",
      "type": "A",
      "difficulty": 3,
      "learningObjectiveId": "lo3",
      "stem": "Welche effektive Dosis wird für Mammographie angegeben?",
      "options": [
        {
          "id": "A",
          "text": "0.35–0.5 mSv",
          "correct": true
        },
        {
          "id": "B",
          "text": "5–10 mSv",
          "correct": false
        },
        {
          "id": "C",
          "text": "20 mSv",
          "correct": false
        },
        {
          "id": "D",
          "text": "50 mSv",
          "correct": false
        },
        {
          "id": "E",
          "text": "Mehrere Gray",
          "correct": false
        }
      ],
      "explanation": "Mammographie besitzt vergleichsweise geringe effektive Dosen.",
      "sourceReliability": "high"
    },
    {
      "id": "q14",
      "type": "A",
      "difficulty": 3,
      "learningObjectiveId": "lo3",
      "stem": "Welche Risikoannahme nennt die Vorlesung?",
      "options": [
        {
          "id": "A",
          "text": "0.5 % Risiko pro mSv",
          "correct": false
        },
        {
          "id": "B",
          "text": "5 % zusätzliches Krebssterberisiko pro 1000 mSv",
          "correct": true
        },
        {
          "id": "C",
          "text": "Kein Risiko unter 100 mSv",
          "correct": false
        },
        {
          "id": "D",
          "text": "Nur Alpha-Strahlung verursacht Krebs",
          "correct": false
        },
        {
          "id": "E",
          "text": "Medizinische Strahlung verursacht immer Krebs",
          "correct": false
        }
      ],
      "explanation": "Die Vorlesung nennt 5 % pro 1000 mSv als häufige Annahme.",
      "sourceReliability": "high"
    },
    {
      "id": "q15",
      "type": "A",
      "difficulty": 3,
      "learningObjectiveId": "lo2",
      "stem": "Welches Ziel verfolgt die Strahlentherapie?",
      "options": [
        {
          "id": "A",
          "text": "Tumorzellen sichtbar machen",
          "correct": false
        },
        {
          "id": "B",
          "text": "Tumorzellen gezielt zerstören bei Schonung gesunden Gewebes",
          "correct": true
        },
        {
          "id": "C",
          "text": "Nur Diagnostik",
          "correct": false
        },
        {
          "id": "D",
          "text": "Nur DNA-Reparatur fördern",
          "correct": false
        },
        {
          "id": "E",
          "text": "Ausschliesslich Bildgebung",
          "correct": false
        }
      ],
      "explanation": "Strahlentherapie appliziert hohe lokalisierte Dosen auf Tumoren.",
      "sourceReliability": "high"
    }
  ]
}